hffs/__init__.py
hffs/main.py
hffs-0.10.dist-info/METADATA
hffs-0.10.dist-info/WHEEL
hffs-0.10.dist-info/entry_points.txt
hffs-0.10.dist-info/top_level.txt
hffs-0.10.dist-info/RECORD
