Metadata-Version: 2.1
Name: hffs
Version: 0.10
Summary: embeddable huggingface downloader web ui
Home-page: https://github.com/cocktailpeanut/huggingfs
Requires-Python: >=3.6
Requires-Dist: gradio
Requires-Dist: huggingface-hub[hf_transfer]
